spiffe/__init__.py
spiffe/bundle/__init__.py
spiffe/bundle/jwt_bundle/__init__.py
spiffe/bundle/jwt_bundle/errors.py
spiffe/bundle/jwt_bundle/jwt_bundle.py
spiffe/bundle/jwt_bundle/jwt_bundle_set.py
spiffe/bundle/x509_bundle/__init__.py
spiffe/bundle/x509_bundle/errors.py
spiffe/bundle/x509_bundle/x509_bundle.py
spiffe/bundle/x509_bundle/x509_bundle_set.py
spiffe/config.py
spiffe/errors.py
spiffe/proto/__init__.py
spiffe/proto/workload.proto
spiffe/proto/workload_pb2.py
spiffe/proto/workload_pb2.pyi
spiffe/proto/workload_pb2_grpc.py
spiffe/spiffe_id/__init__.py
spiffe/spiffe_id/spiffe_id.py
spiffe/svid/__init__.py
spiffe/svid/errors.py
spiffe/svid/jwt_svid.py
spiffe/svid/jwt_svid_validator.py
spiffe/svid/x509_svid.py
spiffe/utils/__init__.py
spiffe/utils/certificate_utils.py
spiffe/utils/errors.py
spiffe/workloadapi/__init__.py
spiffe/workloadapi/errors.py
spiffe/workloadapi/grpc/__init__.py
spiffe/workloadapi/grpc/generic_client_interceptor.py
spiffe/workloadapi/grpc/header_manipulator_client_interceptor.py
spiffe/workloadapi/handle_error.py
spiffe/workloadapi/jwt_source.py
spiffe/workloadapi/workload_api_client.py
spiffe/workloadapi/x509_context.py
spiffe/workloadapi/x509_source.py
spiffe-0.2.3.dist-info/METADATA
spiffe-0.2.3.dist-info/WHEEL
spiffe-0.2.3.dist-info/licenses/LICENSE
spiffe-0.2.3.dist-info/RECORD
