Metadata-Version: 2.4
Name: spiffe
Version: 0.2.3
Summary: Python library for SPIFFE support
License: Apache-2.0
License-File: LICENSE
Author: Max Lambrecht
Author-email: maxlambrecht@gmail.com
Requires-Python: >=3.10,<4.0
Classifier: License :: OSI Approved :: Apache Software License
Classifier: Programming Language :: Python :: 3
Classifier: Programming Language :: Python :: 3.10
Classifier: Programming Language :: Python :: 3.11
Classifier: Programming Language :: Python :: 3.12
Classifier: Programming Language :: Python :: 3.13
Classifier: Programming Language :: Python :: 3.14
Requires-Dist: cryptography (>=45,<47)
Requires-Dist: grpcio (>=1.62,<2.0)
Requires-Dist: pem (>=23.0,<24.0)
Requires-Dist: protobuf (>=5,<7)
Requires-Dist: pyasn1 (>=0.6.0,<0.7.0)
Requires-Dist: pyasn1-modules (>=0.4.0,<0.5.0)
Requires-Dist: pyjwt[crypto] (>=2.0,<3.0)
Project-URL: Repository, https://github.com/HewlettPackard/py-spiffe
